pamiq_recorder/__init__.py
pamiq_recorder/audio.py
pamiq_recorder/base.py
pamiq_recorder/csv.py
pamiq_recorder/jsonl.py
pamiq_recorder/py.typed
pamiq_recorder/video.py
pamiq_recorder-0.3.0.dist-info/METADATA
pamiq_recorder-0.3.0.dist-info/WHEEL
pamiq_recorder-0.3.0.dist-info/licenses/LICENSE
pamiq_recorder-0.3.0.dist-info/RECORD
