Metadata-Version: 2.4
Name: pamiq-recorder
Version: 0.3.0
Summary: Simple, modern, and type-safe recording library for P-AMI<Q>
Project-URL: Repository, https://github.com/MLShukai/pamiq-recorder
Project-URL: Issues, https://github.com/MLShukai/pamiq-recorder/issues
Author-email: Geson-anko <59220704+Geson-anko@users.noreply.github.com>
License-File: LICENSE
Keywords: AMI,Autonomous Machine Intelligence,P-AMI<Q>,audio,csv,opencv,pamiq,recorder,soundfile,video
Classifier: Development Status :: 4 - Beta
Classifier: Intended Audience :: Developers
Classifier: Intended Audience :: Science/Research
Classifier: License :: OSI Approved :: MIT License
Classifier: Natural Language :: English
Classifier: Natural Language :: Japanese
Classifier: Operating System :: POSIX :: Linux
Classifier: Programming Language :: Python
Classifier: Programming Language :: Python :: 3
Classifier: Programming Language :: Python :: 3.12
Classifier: Programming Language :: Python :: 3.13
Classifier: Programming Language :: Python :: 3.14
Requires-Python: >=3.12
Requires-Dist: numpy>=2.2.4
Requires-Dist: opencv-python>=4.11.0.86
Requires-Dist: pamiq-core>=0.2.0
Requires-Dist: soundfile>=0.13.1
